opensourcetest/__init__.py
opensourcetest/__main__.py
opensourcetest/appmodel/.gitignore
opensourcetest/appmodel/ActivityObject/__init__.py
opensourcetest/appmodel/ActivityObject/Login_activity/__init__.py
opensourcetest/appmodel/ActivityObject/Login_activity/Login_activity.yaml
opensourcetest/appmodel/ActivityObject/Login_activity/loginActivity.py
opensourcetest/appmodel/ActivityObject/yamlChoice.py
opensourcetest/appmodel/Base/__init__.py
opensourcetest/appmodel/Base/assertMethod.py
opensourcetest/appmodel/Base/base.py
opensourcetest/appmodel/Common/__init__.py
opensourcetest/appmodel/Common/fileOperation.py
opensourcetest/appmodel/Common/fileOption.py
opensourcetest/appmodel/Common/publicMethod.py
opensourcetest/appmodel/Conf/__init__.py
opensourcetest/appmodel/Conf/config.yaml
opensourcetest/appmodel/conftest.py
opensourcetest/appmodel/Logs/__init__.py
opensourcetest/appmodel/Logs/log.log
opensourcetest/appmodel/pytest.ini
opensourcetest/appmodel/readme.md
opensourcetest/appmodel/run.py
opensourcetest/appmodel/TestCases/__init__.py
opensourcetest/appmodel/TestCases/Login/__init__.py
opensourcetest/appmodel/TestCases/Login/conftest.py
opensourcetest/appmodel/TestCases/Login/test_loginActivityCase.py
opensourcetest/banner/banner_top.txt
opensourcetest/builtin/__init__.py
opensourcetest/builtin/assertChecker.py
opensourcetest/builtin/assertScreenShot.py
opensourcetest/builtin/autoParamInjection.py
opensourcetest/builtin/baseAppRunner.py
opensourcetest/builtin/baseRequest.py
opensourcetest/builtin/baseUiRunner.py
opensourcetest/builtin/check.py
opensourcetest/builtin/exceptions.py
opensourcetest/builtin/locate.py
opensourcetest/builtin/models.py
opensourcetest/builtin/ostDriver.py
opensourcetest/builtin/ostHttp.py
opensourcetest/cli.py
opensourcetest/common/__init__.py
opensourcetest/common/comFileOperation.py
opensourcetest/common/consolelog.py
opensourcetest/common/dockerOperation.py
opensourcetest/common/fileOperation.py
opensourcetest/common/pictureOperation.py
opensourcetest-0.3.24.dist-info/entry_points.txt
opensourcetest-0.3.24.dist-info/LICENSE
opensourcetest-0.3.24.dist-info/METADATA
opensourcetest-0.3.24.dist-info/WHEEL
opensourcetest-0.3.24.dist-info/RECORD
