Metadata-Version: 2.1
Name: opensourcetest
Version: 0.3.24
Summary: We need more free software interface testing.
Home-page: https://github.com/chineseluo/opensourcetest
License: Apache-2.0
Keywords: HTTP,http,Http,api,ui,UI,automated testing,interface,test,requests,pytest,allure,pytest-xdist
Author: chineseluo
Author-email: 848257135@qq.com
Requires-Python: >=3.8,<4.0
Classifier: Development Status :: 4 - Beta
Classifier: License :: OSI Approved :: Apache Software License
Classifier: Operating System :: MacOS
Classifier: Operating System :: Microsoft :: Windows
Classifier: Operating System :: POSIX :: Linux
Classifier: Programming Language :: Python :: 3
Classifier: Programming Language :: Python :: 3.8
Classifier: Programming Language :: Python :: 3.9
Classifier: Programming Language :: Python :: 3.10
Classifier: Programming Language :: Python :: 3.11
Classifier: Programming Language :: Python :: 3.12
Classifier: Programming Language :: Python :: 3.6
Classifier: Programming Language :: Python :: 3.7
Classifier: Topic :: Software Development :: Libraries :: Python Modules
Classifier: Topic :: Software Development :: Quality Assurance
Classifier: Topic :: Software Development :: Testing
Requires-Dist: Appium-Python-Client (==2.11.*)
Requires-Dist: PyYAML (>=5.1.2,<6.0.0)
Requires-Dist: allure-pytest (==2.12.0)
Requires-Dist: allure-python-commons (==2.12.0)
Requires-Dist: docker (>=4.4.0,<5.0.0)
Requires-Dist: jmespath (>=0.9.5,<0.10.0)
Requires-Dist: loguru (>=0.5.3,<0.6.0)
Requires-Dist: mkdocs (>=1.1.2,<2.0.0)
Requires-Dist: mkdocs-material (>=6.0.2,<7.0.0)
Requires-Dist: pydantic (>=1.4,<2.0)
Requires-Dist: pytest (>=5.2,<6.0)
Requires-Dist: pytest-html (>=2.1.1,<3.0.0)
Requires-Dist: requests (>=2.24.0,<3.0.0)
Requires-Dist: requests_toolbelt (==1.0.0)
Requires-Dist: selenium (==4.18.*)
Project-URL: Documentation, http://docs.opensourcetest.cn
Project-URL: Repository, https://github.com/chineseluo/opensourcetest
